orpytlex/classes/downloader.py
orpytlex/main.py
orpytlex-22.6.8.dist-info/entry_points.txt
orpytlex-22.6.8.dist-info/WHEEL
orpytlex-22.6.8.dist-info/METADATA
orpytlex-22.6.8.dist-info/RECORD
